drf_advanced_token_manager/__init__.py
drf_advanced_token_manager/admin.py
drf_advanced_token_manager/apps.py
drf_advanced_token_manager/models.py
drf_advanced_token_manager/tests.py
drf_advanced_token_manager/urls.py
drf_advanced_token_manager/views.py
drf_advanced_token_manager/migrations/__init__.py
drf_advanced_token_manager/templates/drf_token_management_base.html
drf_advanced_token_manager/templates/drf_token_management_change_token.html
drf_advanced_token_manager/templates/drf_token_management_view_token.html
drf_advanced_token_manager-0.1.0.dist-info/LICENSE
drf_advanced_token_manager-0.1.0.dist-info/METADATA
drf_advanced_token_manager-0.1.0.dist-info/WHEEL
drf_advanced_token_manager-0.1.0.dist-info/top_level.txt
drf_advanced_token_manager-0.1.0.dist-info/RECORD
