Metadata-Version: 2.1
Name: drf-advanced-token-manager
Version: 0.1.0
Summary: App level authentication management for django, with access requests and approvals
Home-page: https://github.com/amp89/drf_advanced_token_manager
Author: Alex Peterson
Author-email: contact@alexpeterson.tech
License: MIT
Download-URL: https://github.com/amp89/drf_advanced_token_manager/blob/master/dist/drf_advanced_token_manager-0.1.0.tar.gz
Platform: UNKNOWN
Requires-Python: >=3.6
Requires-Dist: django
Requires-Dist: djangorestframework
Requires-Dist: django-drf-advanced-token
